AUTHORS.rst
ChangeLog.rst
LICENSE
MANIFEST.in
README.md
setup.cfg
setup.py
sanitize/__init__.py
sanitize/config.py
sanitize.egg-info/PKG-INFO
sanitize.egg-info/SOURCES.txt
sanitize.egg-info/dependency_links.txt
sanitize.egg-info/not-zip-safe
sanitize.egg-info/requires.txt
sanitize.egg-info/top_level.txt
tests/__init__.py
tests/test_sanitize_html.py