Metadata-Version: 1.1
Name: sanitize
Version: 2014.10.7
Summary: Bringing sanitiy to world of messed-up data
Home-page: http://www.aaronsw.com/2002/sanitize/
Author: Alireza Savand
Author-email: alireza.savand@gmail.com
License: Redistribution and use in source and binary forms, with or without modification,
